cut_cross_entropy/__init__.py
cut_cross_entropy/cce.py
cut_cross_entropy/cce_backward.py
cut_cross_entropy/cce_lse_forward.py
cut_cross_entropy/constants.py
cut_cross_entropy/doc.py
cut_cross_entropy/indexed_dot.py
cut_cross_entropy/linear_cross_entropy.py
cut_cross_entropy/tl_autotune.py
cut_cross_entropy/tl_utils.py
cut_cross_entropy/torch_compile.py
cut_cross_entropy/utils.py
cut_cross_entropy-24.12.3.dist-info/LICENSE
cut_cross_entropy-24.12.3.dist-info/METADATA
cut_cross_entropy-24.12.3.dist-info/WHEEL
cut_cross_entropy-24.12.3.dist-info/top_level.txt
cut_cross_entropy-24.12.3.dist-info/RECORD
