Metadata-Version: 2.1
Name: cut-cross-entropy
Version: 24.12.3
Summary: Code for cut cross entropy, a memory efficient implementation of linear-cross-entropy loss.
Requires-Python: >=3.10
License-File: LICENSE
Requires-Dist: torch
Requires-Dist: triton; platform_system == "Linux"
Provides-Extra: test
Requires-Dist: pytest; extra == "test"
Provides-Extra: transformers
Requires-Dist: transformers>=4.44.2; extra == "transformers"
Provides-Extra: all
Requires-Dist: cut-cross-entropy[transformers]; extra == "all"
Requires-Dist: deepspeed>=0.15.1; platform_system != "Darwin" and extra == "all"
Requires-Dist: accelerate>=0.34.2; extra == "all"
Requires-Dist: datasets>=3.1.0; extra == "all"
Requires-Dist: huggingface_hub>=0.26.2; extra == "all"
Requires-Dist: pandas; extra == "all"
Requires-Dist: fire; extra == "all"
Requires-Dist: tqdm; extra == "all"
Provides-Extra: dev
Requires-Dist: cut-cross-entropy[all,test]; extra == "dev"
Requires-Dist: build; extra == "dev"
Requires-Dist: twine; extra == "dev"
Requires-Dist: pre-commit; extra == "dev"
